pointr_indoor_location_assistant-0.1.0.dist-info/licenses/LICENSE
src/PointrAgent.py
src/__init__.py
src/app.py
src/requirements.txt
pointr_indoor_location_assistant-0.1.0.dist-info/METADATA
pointr_indoor_location_assistant-0.1.0.dist-info/WHEEL
pointr_indoor_location_assistant-0.1.0.dist-info/top_level.txt
pointr_indoor_location_assistant-0.1.0.dist-info/RECORD
