Metadata-Version: 2.4
Name: pointr-indoor-location-assistant
Version: 0.1.0
Summary: Indoor location assistant using Pointr MCP server to provide QR code navigation for venues.
Author-email: Serhat <support@pointr.tech>
License: MIT License
Project-URL: homepage, https://github.com/yourusername/pointr-indoor-location-assistant
Requires-Python: >=3.13
License-File: LICENSE
Requires-Dist: python-dotenv
Requires-Dist: openai-agents
Dynamic: license-file
